arus_components_hci/__init__.py
arus_components_hci/streams.py
arus_components_hci-0.1.3.dist-info/LICENSE
arus_components_hci-0.1.3.dist-info/WHEEL
arus_components_hci-0.1.3.dist-info/METADATA
arus_components_hci-0.1.3.dist-info/RECORD
