Metadata-Version: 2.1
Name: arus-components-hci
Version: 0.1.3
Summary: arus plugins that include streams, pipelines and broadcasters that may include human computer interactions through GUI, voice or other interfaces.
License: GPL-3.0
Author: qutang
Author-email: tqshelly@gmail.com
Requires-Python: >=3.6,<4.0
Classifier: License :: OSI Approved :: GNU General Public License v3 (GPLv3)
Classifier: Programming Language :: Python :: 3
Classifier: Programming Language :: Python :: 3.6
Classifier: Programming Language :: Python :: 3.7
Requires-Dist: arus (>=0.4.6,<0.5.0)
Requires-Dist: pysimplegui (>=4.4,<5.0)
